{"number":"52.217-4","title":"Evaluation of Options Exercised at Time of Contract Award.","children":[{"text":"As prescribed in 17.208(b), insert a provision substantially the same as the following:","type":"paragraph","level":null},{"text":"Evaluation of Options Exercised at Time of Contract Award (June 1988)","type":"paragraph","level":null},{"text":"Except when it is determined in accordance with FAR 17.206(b) not to be in the Government’s best interests, the Government will evaluate the total price for the basic requirement together with any option(s) exercised at the time of award.","type":"paragraph","level":null},{"text":"(End of provision)","type":"paragraph","level":null}]}
