{"number":"52.236-18","title":"Work Oversight in Cost-Reimbursement Construction Contracts.","children":[{"text":"As prescribed in 36.518, insert the following clause in solicitations and contracts when cost-reimbursement construction contracts are contemplated:","type":"paragraph","level":null},{"text":"Work Oversight in Cost-Reimbursement Construction Contracts (Apr 1984)","type":"paragraph","level":null},{"text":"The extent and character of the work to be done by the Contractor shall be subject to the general supervision, direction, control, and approval of the Contracting Officer.","type":"paragraph","level":null},{"text":"(End of clause)","type":"paragraph","level":null}]}
