{"number":"52.225-14","title":"Inconsistency between English Version and Translation of Contract.","children":[{"text":"As prescribed at 25.1103(b), insert the following clause:","type":"paragraph","level":null},{"text":"Inconsistency Between English Version and Translation of Contract (Feb 2000)","type":"paragraph","level":null},{"text":"In the event of inconsistency between any terms of this contract and any translation into another language, the English language meaning shall control.","type":"paragraph","level":null},{"text":"(End of clause)","type":"paragraph","level":null}]}
