{"number":"8.702","title":"General.","children":[{"text":"The Committee is an independent Government activity with members appointed by the President of the United States. It is responsible for—","type":"paragraph","level":null},{"text":"(a) Determining those supplies and services to be purchased by all entities of the Government from AbilityOne participating nonprofit agencies;","type":"paragraph","level":null},{"text":"(b) Establishing prices for the supplies and services; and","type":"paragraph","level":null},{"text":"(c) Establishing rules and regulations to implement the 41 U.S.C. chapter 85.","type":"paragraph","level":null}]}
